pypi/Client.py
pypi/__init__.py
pypiget-0.2.0.dist-info/METADATA
pypiget-0.2.0.dist-info/WHEEL
pypiget-0.2.0.dist-info/top_level.txt
pypiget-0.2.0.dist-info/RECORD
