Metadata-Version: 2.4
Name: pypiget
Version: 0.2.0
Summary: A Python library to fetch PyPI package information (sync & async)
Home-page: https://api-free.ir
Author: Mahdi Ahmadi
Author-email: mahdiahmadi.1208@gmail.com
Keywords: pypi package async sync fetch library
Classifier: Programming Language :: Python :: 3
Classifier: License :: OSI Approved :: MIT License
Classifier: Operating System :: OS Independent
Classifier: Development Status :: 4 - Beta
Classifier: Intended Audience :: Developers
Classifier: Topic :: Software Development :: Libraries
Requires-Python: >=3.6
Requires-Dist: requests>=2.28.0
Requires-Dist: aiohttp>=3.8.0
Dynamic: author
Dynamic: author-email
Dynamic: classifier
Dynamic: description
Dynamic: description-content-type
Dynamic: home-page
Dynamic: keywords
Dynamic: requires-dist
Dynamic: requires-python
Dynamic: summary
